pascal_voc_analyser/__init__.py
pascal_voc_analyser/voc_analyser.py
pascal_voc_analyser-1.0.1.dist-info/METADATA
pascal_voc_analyser-1.0.1.dist-info/WHEEL
pascal_voc_analyser-1.0.1.dist-info/top_level.txt
pascal_voc_analyser-1.0.1.dist-info/RECORD
