Metadata-Version: 2.1
Name: pascal-voc-analyser
Version: 1.0.1
Summary: Pascal VOC XML annotation format analysis library
Home-page: 
Author: Aman Khatri
Author-email: amankhatri.ai@gmail.com
License: MIT
Classifier: Intended Audience :: Developers
Classifier: License :: OSI Approved :: MIT License
Classifier: Programming Language :: Python
Classifier: Programming Language :: Python :: 3
Classifier: Programming Language :: Python :: 3.6
Classifier: Programming Language :: Python :: 3.7
Classifier: Programming Language :: Python :: 3.8
Classifier: Programming Language :: Python :: 3.9
Classifier: Operating System :: OS Independent
Requires-Dist: dict2xml (==1.7.2)
Requires-Dist: pytest (==7.2.1)
Requires-Dist: xmltodict (==0.13.0)
